mg_sql/__init__.py
mg_sql/_old/sql_raw/README.md
mg_sql/_old/sql_raw/__init__.py
mg_sql/_old/sql_raw/async_sql/__init__.py
mg_sql/_old/sql_raw/async_sql/aiopg_postgres_sql.py
mg_sql/_old/sql_raw/async_sql/async_base_sql.py
mg_sql/_old/sql_raw/async_sql/async_serializer.py
mg_sql/_old/sql_raw/async_sql/asyncpg_postgres_sql.py
mg_sql/_old/sql_raw/base_sql.py
mg_sql/_old/sql_raw/base_user.py
mg_sql/_old/sql_raw/sync_sql/__init__.py
mg_sql/_old/sql_raw/sync_sql/sync_base_sql.py
mg_sql/_old/sql_raw/sync_sql/sync_mysql.py
mg_sql/_old/sql_raw/sync_sql/sync_postgres_sql.py
mg_sql/_old/sql_raw/sync_sql/sync_serializer.py
mg_sql/_old/sql_raw/test/base_dataset_test.py
mg_sql/_old/sql_raw/test/test_postgres.py
mg_sql/_old/sql_raw/test/test_speed.py
mg_sql/_old/sqllite_orm/README.md
mg_sql/_old/sqllite_orm/__init__.py
mg_sql/_old/sqllite_orm/sqllite_orm.py
mg_sql/_old/sqllite_orm/sqlmodules.py
mg_sql/_old/sqllite_orm/test/__init__.py
mg_sql/_old/sqllite_orm/test/test_sqlliteorm.py
mg_sql/sql_async/__init__.py
mg_sql/sql_async/base.py
mg_sql/sql_async/features_sql.py
mg_sql/sql_async/helpful.py
mg_sql/sql_async/model_logic.py
mg_sql-0.0.1.dist-info/WHEEL
mg_sql-0.0.1.dist-info/METADATA
mg_sql-0.0.1.dist-info/RECORD
