Metadata-Version: 2.1
Name: mg-sql
Version: 0.0.1
Summary: Создание файлов конфигурация
Home-page: https://github.com/denisxab/mg_sql.git
Author: Denis Kustov
Author-email: denis-kustov@rambler.ru
Requires-Python: >=3.10,<4.0
Classifier: Programming Language :: Python :: 3
Classifier: Programming Language :: Python :: 3.10
Classifier: Programming Language :: Python :: 3.11
Requires-Dist: SQLAlchemy (>=1.4.39,<2.0.0)
Project-URL: Documentation, https://mg_sql.readthedocs.io/ru/latest/index.html
Project-URL: Repository, https://github.com/denisxab/mg_sql.git
